fmtsrc.py
fmtsrc-0.0.5.dist-info/METADATA
fmtsrc-0.0.5.dist-info/WHEEL
fmtsrc-0.0.5.dist-info/entry_points.txt
fmtsrc-0.0.5.dist-info/top_level.txt
fmtsrc-0.0.5.dist-info/RECORD
