Metadata-Version: 2.1
Name: fmtsrc
Version: 0.0.5
Summary: File or URL formatting
Home-page: https://github.com/yknaka/fmtsrc
Author: yuki nakamura
Author-email: naka_yk@live.jp
License: UNKNOWN
Project-URL: Source File Formatting, https://github.com/yknaka/fmtsrc
Platform: UNKNOWN
Classifier: Programming Language :: Python :: 3
Classifier: License :: OSI Approved :: MIT License
Classifier: Operating System :: OS Independent
Requires-Python: >=3.6
